e2s/__init__.py
e2s/main.py
e2s/py.typed
e2s-1.0.0.dist-info/METADATA
e2s-1.0.0.dist-info/WHEEL
e2s-1.0.0.dist-info/entry_points.txt
e2s-1.0.0.dist-info/licenses/LICENSE
e2s-1.0.0.dist-info/RECORD
